[
  {
    "id": "aarvi-standard-collection-1",
    "source_site": "shipmydeals",
    "url": "",
    "name": "Luster Classy Metal Pen — Black, Gunmetal, Rose Gold",
    "category": "standard-collection",
    "category_label": "Standard Collection",
    "price": "₹20–50",
    "price_numeric": 0,
    "description": "",
    "specifications": {},
    "images": [
      {
        "url": "",
        "local_path": "cropped/low-range-20-50/1.jpg",
        "filename": "1.jpg",
        "is_primary": true,
        "download_status": "success"
      }
    ],
    "scraped_at": "",
    "product_code": "L 177",
    "catalogue_pdf": "low-range-20-50.pdf",
    "catalogue_page": 2,
    "catalogue_image_index": 1
  },
  {
    "id": "aarvi-standard-collection-2",
    "source_site": "shipmydeals",
    "url": "",
    "name": "Rectangle Metal Keychain in Gold Finish",
    "category": "standard-collection",
    "category_label": "Standard Collection",
    "price": "₹20–50",
    "price_numeric": 0,
    "description": "",
    "specifications": {},
    "images": [
      {
        "url": "",
        "local_path": "cropped/low-range-20-50/2.jpg",
        "filename": "2.jpg",
        "is_primary": true,
        "download_status": "success"
      }
    ],
    "scraped_at": "",
    "product_code": "J 116A",
    "catalogue_pdf": "low-range-20-50.pdf",
    "catalogue_page": 3,
    "catalogue_image_index": 2
  },
  {
    "id": "aarvi-standard-collection-3",
    "source_site": "shipmydeals",
    "url": "",
    "name": "Round Metal Keychain with Black Plate Double Side Branding Area",
    "category": "standard-collection",
    "category_label": "Standard Collection",
    "price": "",
    "price_numeric": 0,
    "description": "",
    "specifications": {},
    "images": [
      {
        "url": "",
        "local_path": "cropped/low-range-20-50/3.jpg",
        "filename": "3.jpg",
        "is_primary": true,
        "download_status": "success"
      }
    ],
    "scraped_at": "",
    "product_code": "J 123",
    "catalogue_pdf": "low-range-20-50.pdf",
    "catalogue_page": 4,
    "catalogue_image_index": 3
  },
  {
    "id": "aarvi-standard-collection-4",
    "source_site": "shipmydeals",
    "url": "",
    "name": "Loop Metal Pen with Double Rings",
    "category": "standard-collection",
    "category_label": "Standard Collection",
    "price": "₹20–50",
    "price_numeric": 0,
    "description": "",
    "specifications": {},
    "images": [
      {
        "url": "",
        "local_path": "cropped/low-range-20-50/4.jpg",
        "filename": "4.jpg",
        "is_primary": true,
        "download_status": "success"
      }
    ],
    "scraped_at": "",
    "product_code": "L 175",
    "catalogue_pdf": "low-range-20-50.pdf",
    "catalogue_page": 5,
    "catalogue_image_index": 4
  },
  {
    "id": "aarvi-standard-collection-5",
    "source_site": "shipmydeals",
    "url": "",
    "name": "Black Metal Pen with Colored Highlights",
    "category": "standard-collection",
    "category_label": "Standard Collection",
    "price": "₹20–50",
    "price_numeric": 0,
    "description": "",
    "specifications": {},
    "images": [
      {
        "url": "",
        "local_path": "cropped/low-range-20-50/5.jpg",
        "filename": "5.jpg",
        "is_primary": true,
        "download_status": "success"
      }
    ],
    "scraped_at": "",
    "product_code": "L 174",
    "catalogue_pdf": "low-range-20-50.pdf",
    "catalogue_page": 6,
    "catalogue_image_index": 5
  },
  {
    "id": "aarvi-standard-collection-6",
    "source_site": "shipmydeals",
    "url": "",
    "name": "Gelpen with Paper Clip",
    "category": "standard-collection",
    "category_label": "Standard Collection",
    "price": "₹20–50",
    "price_numeric": 0,
    "description": "",
    "specifications": {},
    "images": [
      {
        "url": "",
        "local_path": "cropped/low-range-20-50/6.jpg",
        "filename": "6.jpg",
        "is_primary": true,
        "download_status": "success"
      }
    ],
    "scraped_at": "",
    "product_code": "L 167",
    "catalogue_pdf": "low-range-20-50.pdf",
    "catalogue_page": 7,
    "catalogue_image_index": 6
  },
  {
    "id": "aarvi-standard-collection-7",
    "source_site": "shipmydeals",
    "url": "",
    "name": "Large Metal Keychain with Bottle Opener — Gunmetal Plate",
    "category": "standard-collection",
    "category_label": "Standard Collection",
    "price": "₹20–50",
    "price_numeric": 0,
    "description": "",
    "specifications": {},
    "images": [
      {
        "url": "",
        "local_path": "cropped/low-range-20-50/7.jpg",
        "filename": "7.jpg",
        "is_primary": true,
        "download_status": "success"
      }
    ],
    "scraped_at": "",
    "product_code": "J 132",
    "catalogue_pdf": "low-range-20-50.pdf",
    "catalogue_page": 8,
    "catalogue_image_index": 7
  },
  {
    "id": "aarvi-standard-collection-8",
    "source_site": "shipmydeals",
    "url": "",
    "name": "Bamboo Eternal Pen Cilwith Rubber",
    "category": "standard-collection",
    "category_label": "Standard Collection",
    "price": "₹20–50",
    "price_numeric": 0,
    "description": "",
    "specifications": {},
    "images": [
      {
        "url": "",
        "local_path": "cropped/low-range-20-50/8.jpg",
        "filename": "8.jpg",
        "is_primary": true,
        "download_status": "success"
      }
    ],
    "scraped_at": "",
    "product_code": "L 160",
    "catalogue_pdf": "low-range-20-50.pdf",
    "catalogue_page": 9,
    "catalogue_image_index": 8
  },
  {
    "id": "aarvi-standard-collection-9",
    "source_site": "shipmydeals",
    "url": "",
    "name": "Table Stand Pen with Double Tape",
    "category": "standard-collection",
    "category_label": "Standard Collection",
    "price": "",
    "price_numeric": 0,
    "description": "",
    "specifications": {},
    "images": [
      {
        "url": "",
        "local_path": "cropped/low-range-20-50/9.jpg",
        "filename": "9.jpg",
        "is_primary": true,
        "download_status": "success"
      }
    ],
    "scraped_at": "",
    "product_code": "L 137",
    "catalogue_pdf": "low-range-20-50.pdf",
    "catalogue_page": 10,
    "catalogue_image_index": 9
  },
  {
    "id": "aarvi-standard-collection-10",
    "source_site": "shipmydeals",
    "url": "",
    "name": "Square Keychain with Torch",
    "category": "standard-collection",
    "category_label": "Standard Collection",
    "price": "₹20–50",
    "price_numeric": 0,
    "description": "",
    "specifications": {},
    "images": [
      {
        "url": "",
        "local_path": "cropped/low-range-20-50/10.jpg",
        "filename": "10.jpg",
        "is_primary": true,
        "download_status": "success"
      }
    ],
    "scraped_at": "",
    "product_code": "J 129",
    "catalogue_pdf": "low-range-20-50.pdf",
    "catalogue_page": 11,
    "catalogue_image_index": 10
  },
  {
    "id": "aarvi-standard-collection-11",
    "source_site": "shipmydeals",
    "url": "",
    "name": "Bamboo Pen with Stylus",
    "category": "standard-collection",
    "category_label": "Standard Collection",
    "price": "",
    "price_numeric": 0,
    "description": "",
    "specifications": {},
    "images": [
      {
        "url": "",
        "local_path": "cropped/low-range-20-50/11.jpg",
        "filename": "11.jpg",
        "is_primary": true,
        "download_status": "success"
      }
    ],
    "scraped_at": "",
    "product_code": "L 151",
    "catalogue_pdf": "low-range-20-50.pdf",
    "catalogue_page": 12,
    "catalogue_image_index": 11
  },
  {
    "id": "aarvi-standard-collection-12",
    "source_site": "shipmydeals",
    "url": "",
    "name": "Metal Bamboo Grip Velvet Finish Pen",
    "category": "standard-collection",
    "category_label": "Standard Collection",
    "price": "₹20–50",
    "price_numeric": 0,
    "description": "",
    "specifications": {},
    "images": [
      {
        "url": "",
        "local_path": "cropped/low-range-20-50/12.jpg",
        "filename": "12.jpg",
        "is_primary": true,
        "download_status": "success"
      }
    ],
    "scraped_at": "",
    "product_code": "L 159",
    "catalogue_pdf": "low-range-20-50.pdf",
    "catalogue_page": 13,
    "catalogue_image_index": 12
  },
  {
    "id": "aarvi-standard-collection-13",
    "source_site": "shipmydeals",
    "url": "",
    "name": "Prism Grip Metal Pen with Stylus",
    "category": "standard-collection",
    "category_label": "Standard Collection",
    "price": "₹20–50",
    "price_numeric": 0,
    "description": "",
    "specifications": {},
    "images": [
      {
        "url": "",
        "local_path": "cropped/low-range-20-50/13.jpg",
        "filename": "13.jpg",
        "is_primary": true,
        "download_status": "success"
      }
    ],
    "scraped_at": "",
    "product_code": "L 153",
    "catalogue_pdf": "low-range-20-50.pdf",
    "catalogue_page": 14,
    "catalogue_image_index": 13
  },
  {
    "id": "aarvi-standard-collection-14",
    "source_site": "shipmydeals",
    "url": "",
    "name": "Matte Metal Pen with Colored Highlights",
    "category": "standard-collection",
    "category_label": "Standard Collection",
    "price": "₹20–50",
    "price_numeric": 0,
    "description": "",
    "specifications": {},
    "images": [
      {
        "url": "",
        "local_path": "cropped/low-range-20-50/14.jpg",
        "filename": "14.jpg",
        "is_primary": true,
        "download_status": "success"
      }
    ],
    "scraped_at": "",
    "product_code": "L 154",
    "catalogue_pdf": "low-range-20-50.pdf",
    "catalogue_page": 15,
    "catalogue_image_index": 14
  },
  {
    "id": "aarvi-standard-collection-15",
    "source_site": "shipmydeals",
    "url": "",
    "name": "6 in 1 Pen with Phone Stand, Cleaner, Ruler and Tools and Stylus",
    "category": "standard-collection",
    "category_label": "Standard Collection",
    "price": "",
    "price_numeric": 0,
    "description": "",
    "specifications": {},
    "images": [
      {
        "url": "",
        "local_path": "cropped/low-range-20-50/15.jpg",
        "filename": "15.jpg",
        "is_primary": true,
        "download_status": "success"
      }
    ],
    "scraped_at": "",
    "product_code": "L 145",
    "catalogue_pdf": "low-range-20-50.pdf",
    "catalogue_page": 16,
    "catalogue_image_index": 15
  },
  {
    "id": "aarvi-standard-collection-16",
    "source_site": "shipmydeals",
    "url": "",
    "name": "Hut Shape Metal Keychain in Gunmetal Finish",
    "category": "standard-collection",
    "category_label": "Standard Collection",
    "price": "",
    "price_numeric": 0,
    "description": "",
    "specifications": {},
    "images": [
      {
        "url": "",
        "local_path": "cropped/low-range-20-50/17.jpg",
        "filename": "17.jpg",
        "is_primary": true,
        "download_status": "success"
      }
    ],
    "scraped_at": "",
    "product_code": "J 126",
    "catalogue_pdf": "low-range-20-50.pdf",
    "catalogue_page": 17,
    "catalogue_image_index": 16
  },
  {
    "id": "aarvi-standard-collection-17",
    "source_site": "shipmydeals",
    "url": "",
    "name": "4 in 1 Pen with Mobile Stand, Stylus & Cleaner",
    "category": "standard-collection",
    "category_label": "Standard Collection",
    "price": "",
    "price_numeric": 0,
    "description": "",
    "specifications": {},
    "images": [
      {
        "url": "",
        "local_path": "cropped/low-range-20-50/18.jpg",
        "filename": "18.jpg",
        "is_primary": true,
        "download_status": "success"
      }
    ],
    "scraped_at": "",
    "product_code": "L 124",
    "catalogue_pdf": "low-range-20-50.pdf",
    "catalogue_page": 18,
    "catalogue_image_index": 17
  },
  {
    "id": "aarvi-standard-collection-18",
    "source_site": "shipmydeals",
    "url": "",
    "name": "Logo Highlight Keychain",
    "category": "standard-collection",
    "category_label": "Standard Collection",
    "price": "",
    "price_numeric": 0,
    "description": "",
    "specifications": {},
    "images": [
      {
        "url": "",
        "local_path": "cropped/low-range-20-50/19.jpg",
        "filename": "19.jpg",
        "is_primary": true,
        "download_status": "success"
      }
    ],
    "scraped_at": "",
    "product_code": "J 122",
    "catalogue_pdf": "low-range-20-50.pdf",
    "catalogue_page": 19,
    "catalogue_image_index": 18
  },
  {
    "id": "aarvi-standard-collection-19",
    "source_site": "shipmydeals",
    "url": "",
    "name": "Memo Mr. Memo Holder",
    "category": "standard-collection",
    "category_label": "Standard Collection",
    "price": "",
    "price_numeric": 0,
    "description": "",
    "specifications": {},
    "images": [
      {
        "url": "",
        "local_path": "cropped/low-range-20-50/20.jpg",
        "filename": "20.jpg",
        "is_primary": true,
        "download_status": "success"
      }
    ],
    "scraped_at": "",
    "product_code": "E 07",
    "catalogue_pdf": "low-range-20-50.pdf",
    "catalogue_page": 20,
    "catalogue_image_index": 19
  },
  {
    "id": "aarvi-standard-collection-20",
    "source_site": "shipmydeals",
    "url": "",
    "name": "10 Ml Sanitizer Spray Bottle",
    "category": "standard-collection",
    "category_label": "Standard Collection",
    "price": "",
    "price_numeric": 0,
    "description": "",
    "specifications": {},
    "images": [
      {
        "url": "",
        "local_path": "cropped/low-range-20-50/21.jpg",
        "filename": "21.jpg",
        "is_primary": true,
        "download_status": "success"
      }
    ],
    "scraped_at": "",
    "product_code": "M 18A",
    "catalogue_pdf": "low-range-20-50.pdf",
    "catalogue_page": 21,
    "catalogue_image_index": 20
  },
  {
    "id": "aarvi-standard-collection-21",
    "source_site": "shipmydeals",
    "url": "",
    "name": "Handy Sealer",
    "category": "standard-collection",
    "category_label": "Standard Collection",
    "price": "",
    "price_numeric": 0,
    "description": "",
    "specifications": {},
    "images": [
      {
        "url": "",
        "local_path": "cropped/low-range-20-50/22.jpg",
        "filename": "22.jpg",
        "is_primary": true,
        "download_status": "success"
      }
    ],
    "scraped_at": "",
    "product_code": "Z 07",
    "catalogue_pdf": "low-range-20-50.pdf",
    "catalogue_page": 22,
    "catalogue_image_index": 21
  },
  {
    "id": "aarvi-standard-collection-22",
    "source_site": "shipmydeals",
    "url": "",
    "name": "Face Shield with Plastic Headband",
    "category": "standard-collection",
    "category_label": "Standard Collection",
    "price": "",
    "price_numeric": 0,
    "description": "",
    "specifications": {},
    "images": [
      {
        "url": "",
        "local_path": "cropped/low-range-20-50/23.jpg",
        "filename": "23.jpg",
        "is_primary": true,
        "download_status": "success"
      }
    ],
    "scraped_at": "",
    "product_code": "E 276",
    "catalogue_pdf": "low-range-20-50.pdf",
    "catalogue_page": 23,
    "catalogue_image_index": 22
  },
  {
    "id": "aarvi-standard-collection-23",
    "source_site": "shipmydeals",
    "url": "",
    "name": "Set of 20 Paper Clips with Box",
    "category": "standard-collection",
    "category_label": "Standard Collection",
    "price": "",
    "price_numeric": 0,
    "description": "",
    "specifications": {},
    "images": [
      {
        "url": "",
        "local_path": "cropped/low-range-20-50/24.jpg",
        "filename": "24.jpg",
        "is_primary": true,
        "download_status": "success"
      }
    ],
    "scraped_at": "",
    "product_code": "B 31",
    "catalogue_pdf": "low-range-20-50.pdf",
    "catalogue_page": 24,
    "catalogue_image_index": 23
  },
  {
    "id": "aarvi-standard-collection-24",
    "source_site": "shipmydeals",
    "url": "",
    "name": "Logo Highlight Keychain White Backlight",
    "category": "standard-collection",
    "category_label": "Standard Collection",
    "price": "",
    "price_numeric": 0,
    "description": "",
    "specifications": {},
    "images": [
      {
        "url": "",
        "local_path": "cropped/low-range-20-50/25.jpg",
        "filename": "25.jpg",
        "is_primary": true,
        "download_status": "success"
      }
    ],
    "scraped_at": "",
    "product_code": "J 114",
    "catalogue_pdf": "low-range-20-50.pdf",
    "catalogue_page": 25,
    "catalogue_image_index": 24
  },
  {
    "id": "aarvi-standard-collection-25",
    "source_site": "shipmydeals",
    "url": "",
    "name": "Pizza Cutter with Server",
    "category": "standard-collection",
    "category_label": "Standard Collection",
    "price": "",
    "price_numeric": 0,
    "description": "",
    "specifications": {},
    "images": [
      {
        "url": "",
        "local_path": "cropped/low-range-20-50/26.jpg",
        "filename": "26.jpg",
        "is_primary": true,
        "download_status": "success"
      }
    ],
    "scraped_at": "",
    "product_code": "Z 06",
    "catalogue_pdf": "low-range-20-50.pdf",
    "catalogue_page": 26,
    "catalogue_image_index": 25
  },
  {
    "id": "aarvi-standard-collection-26",
    "source_site": "shipmydeals",
    "url": "",
    "name": "Nail Filer with Nail Protector",
    "category": "standard-collection",
    "category_label": "Standard Collection",
    "price": "",
    "price_numeric": 0,
    "description": "",
    "specifications": {},
    "images": [
      {
        "url": "",
        "local_path": "cropped/low-range-20-50/27.jpg",
        "filename": "27.jpg",
        "is_primary": true,
        "download_status": "success"
      }
    ],
    "scraped_at": "",
    "product_code": "N 19",
    "catalogue_pdf": "low-range-20-50.pdf",
    "catalogue_page": 27,
    "catalogue_image_index": 26
  },
  {
    "id": "aarvi-standard-collection-27",
    "source_site": "shipmydeals",
    "url": "",
    "name": "Folding Mirror with Sewing Kit D Shape",
    "category": "standard-collection",
    "category_label": "Standard Collection",
    "price": "",
    "price_numeric": 0,
    "description": "",
    "specifications": {},
    "images": [
      {
        "url": "",
        "local_path": "cropped/low-range-20-50/28.jpg",
        "filename": "28.jpg",
        "is_primary": true,
        "download_status": "success"
      }
    ],
    "scraped_at": "",
    "product_code": "N 18",
    "catalogue_pdf": "low-range-20-50.pdf",
    "catalogue_page": 28,
    "catalogue_image_index": 27
  },
  {
    "id": "aarvi-standard-collection-28",
    "source_site": "shipmydeals",
    "url": "",
    "name": "Folding 2 Side Mirror Folding Double Mirror",
    "category": "standard-collection",
    "category_label": "Standard Collection",
    "price": "",
    "price_numeric": 0,
    "description": "",
    "specifications": {},
    "images": [
      {
        "url": "",
        "local_path": "cropped/low-range-20-50/29.jpg",
        "filename": "29.jpg",
        "is_primary": true,
        "download_status": "success"
      }
    ],
    "scraped_at": "",
    "product_code": "N 16",
    "catalogue_pdf": "low-range-20-50.pdf",
    "catalogue_page": 29,
    "catalogue_image_index": 28
  },
  {
    "id": "aarvi-standard-collection-29",
    "source_site": "shipmydeals",
    "url": "",
    "name": "Oval Flat Pen",
    "category": "standard-collection",
    "category_label": "Standard Collection",
    "price": "",
    "price_numeric": 0,
    "description": "",
    "specifications": {},
    "images": [
      {
        "url": "",
        "local_path": "cropped/low-range-20-50/30.jpg",
        "filename": "30.jpg",
        "is_primary": true,
        "download_status": "success"
      }
    ],
    "scraped_at": "",
    "product_code": "L 140",
    "catalogue_pdf": "low-range-20-50.pdf",
    "catalogue_page": 30,
    "catalogue_image_index": 29
  },
  {
    "id": "aarvi-standard-collection-30",
    "source_site": "shipmydeals",
    "url": "",
    "name": "Pen with Safety Cutter / Letter Opener",
    "category": "standard-collection",
    "category_label": "Standard Collection",
    "price": "",
    "price_numeric": 0,
    "description": "",
    "specifications": {},
    "images": [
      {
        "url": "",
        "local_path": "cropped/low-range-20-50/31.jpg",
        "filename": "31.jpg",
        "is_primary": true,
        "download_status": "success"
      }
    ],
    "scraped_at": "",
    "product_code": "L 121",
    "catalogue_pdf": "low-range-20-50.pdf",
    "catalogue_page": 31,
    "catalogue_image_index": 30
  },
  {
    "id": "aarvi-standard-collection-31",
    "source_site": "shipmydeals",
    "url": "",
    "name": "Easy Grip Classy Metal Pen",
    "category": "standard-collection",
    "category_label": "Standard Collection",
    "price": "",
    "price_numeric": 0,
    "description": "",
    "specifications": {},
    "images": [
      {
        "url": "",
        "local_path": "cropped/low-range-20-50/32.jpg",
        "filename": "32.jpg",
        "is_primary": true,
        "download_status": "success"
      }
    ],
    "scraped_at": "",
    "product_code": "L 108",
    "catalogue_pdf": "low-range-20-50.pdf",
    "catalogue_page": 32,
    "catalogue_image_index": 31
  },
  {
    "id": "aarvi-standard-collection-32",
    "source_site": "shipmydeals",
    "url": "",
    "name": "Single PC Gel Highlighter",
    "category": "standard-collection",
    "category_label": "Standard Collection",
    "price": "",
    "price_numeric": 0,
    "description": "",
    "specifications": {},
    "images": [
      {
        "url": "",
        "local_path": "cropped/low-range-20-50/33.jpg",
        "filename": "33.jpg",
        "is_primary": true,
        "download_status": "success"
      }
    ],
    "scraped_at": "",
    "product_code": "L 104",
    "catalogue_pdf": "low-range-20-50.pdf",
    "catalogue_page": 33,
    "catalogue_image_index": 32
  },
  {
    "id": "aarvi-standard-collection-33",
    "source_site": "shipmydeals",
    "url": "",
    "name": "Set of Pen with Mechanical Pencil (0.7 Mm",
    "category": "standard-collection",
    "category_label": "Standard Collection",
    "price": "",
    "price_numeric": 0,
    "description": "",
    "specifications": {},
    "images": [
      {
        "url": "",
        "local_path": "cropped/low-range-20-50/34.jpg",
        "filename": "34.jpg",
        "is_primary": true,
        "download_status": "success"
      }
    ],
    "scraped_at": "",
    "product_code": "L 92",
    "catalogue_pdf": "low-range-20-50.pdf",
    "catalogue_page": 34,
    "catalogue_image_index": 33
  },
  {
    "id": "aarvi-standard-collection-34",
    "source_site": "shipmydeals",
    "url": "",
    "name": "Twisty 3 Refill Pen with Stylus (ultra Sleek",
    "category": "standard-collection",
    "category_label": "Standard Collection",
    "price": "",
    "price_numeric": 0,
    "description": "",
    "specifications": {},
    "images": [
      {
        "url": "",
        "local_path": "cropped/low-range-20-50/35.jpg",
        "filename": "35.jpg",
        "is_primary": true,
        "download_status": "success"
      }
    ],
    "scraped_at": "",
    "product_code": "L 91",
    "catalogue_pdf": "low-range-20-50.pdf",
    "catalogue_page": 35,
    "catalogue_image_index": 34
  },
  {
    "id": "aarvi-standard-collection-35",
    "source_site": "shipmydeals",
    "url": "",
    "name": "Stylus with Pen and Highlighter",
    "category": "standard-collection",
    "category_label": "Standard Collection",
    "price": "",
    "price_numeric": 0,
    "description": "",
    "specifications": {},
    "images": [
      {
        "url": "",
        "local_path": "cropped/low-range-20-50/36.jpg",
        "filename": "36.jpg",
        "is_primary": true,
        "download_status": "success"
      }
    ],
    "scraped_at": "",
    "product_code": "L 80",
    "catalogue_pdf": "low-range-20-50.pdf",
    "catalogue_page": 36,
    "catalogue_image_index": 35
  },
  {
    "id": "aarvi-standard-collection-36",
    "source_site": "shipmydeals",
    "url": "",
    "name": "Pen with Highlighter & Stylus",
    "category": "standard-collection",
    "category_label": "Standard Collection",
    "price": "",
    "price_numeric": 0,
    "description": "",
    "specifications": {},
    "images": [
      {
        "url": "",
        "local_path": "cropped/low-range-20-50/37.jpg",
        "filename": "37.jpg",
        "is_primary": true,
        "download_status": "success"
      }
    ],
    "scraped_at": "",
    "product_code": "L 75",
    "catalogue_pdf": "low-range-20-50.pdf",
    "catalogue_page": 37,
    "catalogue_image_index": 36
  },
  {
    "id": "aarvi-standard-collection-37",
    "source_site": "shipmydeals",
    "url": "",
    "name": "Pen with 2 Way Screwdriver",
    "category": "standard-collection",
    "category_label": "Standard Collection",
    "price": "",
    "price_numeric": 0,
    "description": "",
    "specifications": {},
    "images": [
      {
        "url": "",
        "local_path": "cropped/low-range-20-50/38.jpg",
        "filename": "38.jpg",
        "is_primary": true,
        "download_status": "success"
      }
    ],
    "scraped_at": "",
    "product_code": "L 46",
    "catalogue_pdf": "low-range-20-50.pdf",
    "catalogue_page": 38,
    "catalogue_image_index": 37
  },
  {
    "id": "aarvi-standard-collection-38",
    "source_site": "shipmydeals",
    "url": "",
    "name": "Metal Grip Pen",
    "category": "standard-collection",
    "category_label": "Standard Collection",
    "price": "",
    "price_numeric": 0,
    "description": "",
    "specifications": {},
    "images": [
      {
        "url": "",
        "local_path": "cropped/low-range-20-50/39.jpg",
        "filename": "39.jpg",
        "is_primary": true,
        "download_status": "success"
      }
    ],
    "scraped_at": "",
    "product_code": "L 35",
    "catalogue_pdf": "low-range-20-50.pdf",
    "catalogue_page": 39,
    "catalogue_image_index": 38
  },
  {
    "id": "aarvi-standard-collection-39",
    "source_site": "shipmydeals",
    "url": "",
    "name": "Rectangle Metal Keychain in Black Finish Double Side Laser",
    "category": "standard-collection",
    "category_label": "Standard Collection",
    "price": "",
    "price_numeric": 0,
    "description": "",
    "specifications": {},
    "images": [
      {
        "url": "",
        "local_path": "cropped/low-range-20-50/40.jpg",
        "filename": "40.jpg",
        "is_primary": true,
        "download_status": "success"
      }
    ],
    "scraped_at": "",
    "product_code": "J 116",
    "catalogue_pdf": "low-range-20-50.pdf",
    "catalogue_page": 40,
    "catalogue_image_index": 39
  },
  {
    "id": "aarvi-standard-collection-40",
    "source_site": "shipmydeals",
    "url": "",
    "name": "Logo Highlight Keychain Multicolor Backlight",
    "category": "standard-collection",
    "category_label": "Standard Collection",
    "price": "",
    "price_numeric": 0,
    "description": "",
    "specifications": {},
    "images": [
      {
        "url": "",
        "local_path": "cropped/low-range-20-50/41.jpg",
        "filename": "41.jpg",
        "is_primary": true,
        "download_status": "success"
      }
    ],
    "scraped_at": "",
    "product_code": "J 115",
    "catalogue_pdf": "low-range-20-50.pdf",
    "catalogue_page": 41,
    "catalogue_image_index": 40
  },
  {
    "id": "aarvi-standard-collection-41",
    "source_site": "shipmydeals",
    "url": "",
    "name": "Droplet Shape Keychain with Highlights",
    "category": "standard-collection",
    "category_label": "Standard Collection",
    "price": "",
    "price_numeric": 0,
    "description": "",
    "specifications": {},
    "images": [
      {
        "url": "",
        "local_path": "cropped/low-range-20-50/42.jpg",
        "filename": "42.jpg",
        "is_primary": true,
        "download_status": "success"
      }
    ],
    "scraped_at": "",
    "product_code": "J 92",
    "catalogue_pdf": "low-range-20-50.pdf",
    "catalogue_page": 42,
    "catalogue_image_index": 41
  },
  {
    "id": "aarvi-standard-collection-42",
    "source_site": "shipmydeals",
    "url": "",
    "name": "Girl Shape Keychain with Red Highlights",
    "category": "standard-collection",
    "category_label": "Standard Collection",
    "price": "",
    "price_numeric": 0,
    "description": "",
    "specifications": {},
    "images": [
      {
        "url": "",
        "local_path": "cropped/low-range-20-50/43.jpg",
        "filename": "43.jpg",
        "is_primary": true,
        "download_status": "success"
      }
    ],
    "scraped_at": "",
    "product_code": "J 89",
    "catalogue_pdf": "low-range-20-50.pdf",
    "catalogue_page": 43,
    "catalogue_image_index": 42
  },
  {
    "id": "aarvi-standard-collection-43",
    "source_site": "shipmydeals",
    "url": "",
    "name": "Heart Shape Keychain with Highlights",
    "category": "standard-collection",
    "category_label": "Standard Collection",
    "price": "",
    "price_numeric": 0,
    "description": "",
    "specifications": {},
    "images": [
      {
        "url": "",
        "local_path": "cropped/low-range-20-50/44.jpg",
        "filename": "44.jpg",
        "is_primary": true,
        "download_status": "success"
      }
    ],
    "scraped_at": "",
    "product_code": "J 88",
    "catalogue_pdf": "low-range-20-50.pdf",
    "catalogue_page": 44,
    "catalogue_image_index": 43
  },
  {
    "id": "aarvi-standard-collection-44",
    "source_site": "shipmydeals",
    "url": "",
    "name": "Flash Tag with Whistle and Torch",
    "category": "standard-collection",
    "category_label": "Standard Collection",
    "price": "",
    "price_numeric": 0,
    "description": "",
    "specifications": {},
    "images": [
      {
        "url": "",
        "local_path": "cropped/low-range-20-50/45.jpg",
        "filename": "45.jpg",
        "is_primary": true,
        "download_status": "success"
      }
    ],
    "scraped_at": "",
    "product_code": "J 86",
    "catalogue_pdf": "low-range-20-50.pdf",
    "catalogue_page": 45,
    "catalogue_image_index": 44
  },
  {
    "id": "aarvi-standard-collection-45",
    "source_site": "shipmydeals",
    "url": "",
    "name": "Easilyopenbeverageandpackagedfoodcans Universal Bottle and Can Opener",
    "category": "standard-collection",
    "category_label": "Standard Collection",
    "price": "",
    "price_numeric": 0,
    "description": "",
    "specifications": {},
    "images": [
      {
        "url": "",
        "local_path": "cropped/low-range-20-50/46.jpg",
        "filename": "46.jpg",
        "is_primary": true,
        "download_status": "success"
      }
    ],
    "scraped_at": "",
    "product_code": "J 84",
    "catalogue_pdf": "low-range-20-50.pdf",
    "catalogue_page": 46,
    "catalogue_image_index": 45
  },
  {
    "id": "aarvi-standard-collection-46",
    "source_site": "shipmydeals",
    "url": "",
    "name": "Made of BPA Free, Banana Finger Sipper",
    "category": "standard-collection",
    "category_label": "Standard Collection",
    "price": "",
    "price_numeric": 0,
    "description": "",
    "specifications": {},
    "images": [
      {
        "url": "",
        "local_path": "cropped/low-range-20-50/47.jpg",
        "filename": "47.jpg",
        "is_primary": true,
        "download_status": "success"
      }
    ],
    "scraped_at": "",
    "product_code": "H 105",
    "catalogue_pdf": "low-range-20-50.pdf",
    "catalogue_page": 47,
    "catalogue_image_index": 46
  },
  {
    "id": "aarvi-standard-collection-47",
    "source_site": "shipmydeals",
    "url": "",
    "name": "Madeof Bpafree, Angel Water Bottle",
    "category": "standard-collection",
    "category_label": "Standard Collection",
    "price": "",
    "price_numeric": 0,
    "description": "",
    "specifications": {},
    "images": [
      {
        "url": "",
        "local_path": "cropped/low-range-20-50/48.jpg",
        "filename": "48.jpg",
        "is_primary": true,
        "download_status": "success"
      }
    ],
    "scraped_at": "",
    "product_code": "H 74",
    "catalogue_pdf": "low-range-20-50.pdf",
    "catalogue_page": 48,
    "catalogue_image_index": 47
  },
  {
    "id": "aarvi-standard-collection-48",
    "source_site": "shipmydeals",
    "url": "",
    "name": "Gr Ippy Water Bottl E - H 6 5 800 Ml",
    "category": "standard-collection",
    "category_label": "Standard Collection",
    "price": "",
    "price_numeric": 0,
    "description": "",
    "specifications": {},
    "images": [
      {
        "url": "",
        "local_path": "cropped/low-range-20-50/49.jpg",
        "filename": "49.jpg",
        "is_primary": true,
        "download_status": "success"
      }
    ],
    "scraped_at": "",
    "product_code": "H 6",
    "catalogue_pdf": "low-range-20-50.pdf",
    "catalogue_page": 49,
    "catalogue_image_index": 48
  },
  {
    "id": "aarvi-standard-collection-49",
    "source_site": "shipmydeals",
    "url": "",
    "name": "Dumbbell Shape Water Bottle(small",
    "category": "standard-collection",
    "category_label": "Standard Collection",
    "price": "",
    "price_numeric": 0,
    "description": "",
    "specifications": {},
    "images": [
      {
        "url": "",
        "local_path": "cropped/low-range-20-50/50.jpg",
        "filename": "50.jpg",
        "is_primary": true,
        "download_status": "success"
      }
    ],
    "scraped_at": "",
    "product_code": "H 62",
    "catalogue_pdf": "low-range-20-50.pdf",
    "catalogue_page": 50,
    "catalogue_image_index": 49
  },
  {
    "id": "aarvi-standard-collection-50",
    "source_site": "shipmydeals",
    "url": "",
    "name": "Water Bottle (blue/Red/Yellow",
    "category": "standard-collection",
    "category_label": "Standard Collection",
    "price": "",
    "price_numeric": 0,
    "description": "",
    "specifications": {},
    "images": [
      {
        "url": "",
        "local_path": "cropped/low-range-20-50/51.jpg",
        "filename": "51.jpg",
        "is_primary": true,
        "download_status": "success"
      }
    ],
    "scraped_at": "",
    "product_code": "H 15",
    "catalogue_pdf": "low-range-20-50.pdf",
    "catalogue_page": 51,
    "catalogue_image_index": 50
  },
  {
    "id": "aarvi-standard-collection-51",
    "source_site": "shipmydeals",
    "url": "",
    "name": "Plastic Water Bottle Small",
    "category": "standard-collection",
    "category_label": "Standard Collection",
    "price": "",
    "price_numeric": 0,
    "description": "",
    "specifications": {},
    "images": [
      {
        "url": "",
        "local_path": "cropped/low-range-20-50/52.jpg",
        "filename": "52.jpg",
        "is_primary": true,
        "download_status": "success"
      }
    ],
    "scraped_at": "",
    "product_code": "H 13",
    "catalogue_pdf": "low-range-20-50.pdf",
    "catalogue_page": 52,
    "catalogue_image_index": 51
  },
  {
    "id": "aarvi-standard-collection-52",
    "source_site": "shipmydeals",
    "url": "",
    "name": "Rotating Mobile Finger Ring",
    "category": "standard-collection",
    "category_label": "Standard Collection",
    "price": "",
    "price_numeric": 0,
    "description": "",
    "specifications": {},
    "images": [
      {
        "url": "",
        "local_path": "cropped/low-range-20-50/53.jpg",
        "filename": "53.jpg",
        "is_primary": true,
        "download_status": "success"
      }
    ],
    "scraped_at": "",
    "product_code": "E 191",
    "catalogue_pdf": "low-range-20-50.pdf",
    "catalogue_page": 53,
    "catalogue_image_index": 52
  },
  {
    "id": "aarvi-standard-collection-53",
    "source_site": "shipmydeals",
    "url": "",
    "name": "Dilbert Style Mobile Stand",
    "category": "standard-collection",
    "category_label": "Standard Collection",
    "price": "",
    "price_numeric": 0,
    "description": "",
    "specifications": {},
    "images": [
      {
        "url": "",
        "local_path": "cropped/low-range-20-50/54.jpg",
        "filename": "54.jpg",
        "is_primary": true,
        "download_status": "success"
      }
    ],
    "scraped_at": "",
    "product_code": "E 164",
    "catalogue_pdf": "low-range-20-50.pdf",
    "catalogue_page": 54,
    "catalogue_image_index": 53
  },
  {
    "id": "aarvi-standard-collection-54",
    "source_site": "shipmydeals",
    "url": "",
    "name": "Muscle Man Bottle Opener",
    "category": "standard-collection",
    "category_label": "Standard Collection",
    "price": "",
    "price_numeric": 0,
    "description": "",
    "specifications": {},
    "images": [
      {
        "url": "",
        "local_path": "cropped/low-range-20-50/55.jpg",
        "filename": "55.jpg",
        "is_primary": true,
        "download_status": "success"
      }
    ],
    "scraped_at": "",
    "product_code": "E 157",
    "catalogue_pdf": "low-range-20-50.pdf",
    "catalogue_page": 55,
    "catalogue_image_index": 54
  },
  {
    "id": "aarvi-standard-collection-55",
    "source_site": "shipmydeals",
    "url": "",
    "name": "Mobile & Tablet Stand with Stylus and Pen",
    "category": "standard-collection",
    "category_label": "Standard Collection",
    "price": "",
    "price_numeric": 0,
    "description": "",
    "specifications": {},
    "images": [
      {
        "url": "",
        "local_path": "cropped/low-range-20-50/56.jpg",
        "filename": "56.jpg",
        "is_primary": true,
        "download_status": "success"
      }
    ],
    "scraped_at": "",
    "product_code": "E 153",
    "catalogue_pdf": "low-range-20-50.pdf",
    "catalogue_page": 56,
    "catalogue_image_index": 55
  },
  {
    "id": "aarvi-standard-collection-56",
    "source_site": "shipmydeals",
    "url": "",
    "name": "Inchesindiameter Prevents Accidental Knocking Over of Your Cup Clippy Cup Holder",
    "category": "standard-collection",
    "category_label": "Standard Collection",
    "price": "",
    "price_numeric": 0,
    "description": "",
    "specifications": {},
    "images": [
      {
        "url": "",
        "local_path": "cropped/low-range-20-50/57.jpg",
        "filename": "57.jpg",
        "is_primary": true,
        "download_status": "success"
      }
    ],
    "scraped_at": "",
    "product_code": "E 139",
    "catalogue_pdf": "low-range-20-50.pdf",
    "catalogue_page": 57,
    "catalogue_image_index": 56
  },
  {
    "id": "aarvi-standard-collection-57",
    "source_site": "shipmydeals",
    "url": "",
    "name": "Multi Mobile Band (multipurpose Removable Pocket",
    "category": "standard-collection",
    "category_label": "Standard Collection",
    "price": "",
    "price_numeric": 0,
    "description": "",
    "specifications": {},
    "images": [
      {
        "url": "",
        "local_path": "cropped/low-range-20-50/58.jpg",
        "filename": "58.jpg",
        "is_primary": true,
        "download_status": "success"
      }
    ],
    "scraped_at": "",
    "product_code": "E 133",
    "catalogue_pdf": "low-range-20-50.pdf",
    "catalogue_page": 58,
    "catalogue_image_index": 57
  },
  {
    "id": "aarvi-standard-collection-58",
    "source_site": "shipmydeals",
    "url": "",
    "name": "Jack Stylus with Mobile Stand",
    "category": "standard-collection",
    "category_label": "Standard Collection",
    "price": "",
    "price_numeric": 0,
    "description": "",
    "specifications": {},
    "images": [
      {
        "url": "",
        "local_path": "cropped/low-range-20-50/59.jpg",
        "filename": "59.jpg",
        "is_primary": true,
        "download_status": "success"
      }
    ],
    "scraped_at": "",
    "product_code": "E 113",
    "catalogue_pdf": "low-range-20-50.pdf",
    "catalogue_page": 59,
    "catalogue_image_index": 58
  },
  {
    "id": "aarvi-standard-collection-59",
    "source_site": "shipmydeals",
    "url": "",
    "name": "Siliconvacuummobile Stand with Comesin Three Earphone Holder",
    "category": "standard-collection",
    "category_label": "Standard Collection",
    "price": "",
    "price_numeric": 0,
    "description": "",
    "specifications": {},
    "images": [
      {
        "url": "",
        "local_path": "cropped/low-range-20-50/60.jpg",
        "filename": "60.jpg",
        "is_primary": true,
        "download_status": "success"
      }
    ],
    "scraped_at": "",
    "product_code": "E 98",
    "catalogue_pdf": "low-range-20-50.pdf",
    "catalogue_page": 60,
    "catalogue_image_index": 59
  },
  {
    "id": "aarvi-standard-collection-60",
    "source_site": "shipmydeals",
    "url": "",
    "name": "Salt Egg Shape Salt & Pepper Shaker Set with Stand",
    "category": "standard-collection",
    "category_label": "Standard Collection",
    "price": "",
    "price_numeric": 0,
    "description": "",
    "specifications": {},
    "images": [
      {
        "url": "",
        "local_path": "cropped/low-range-20-50/61.jpg",
        "filename": "61.jpg",
        "is_primary": true,
        "download_status": "success"
      }
    ],
    "scraped_at": "",
    "product_code": "E 91",
    "catalogue_pdf": "low-range-20-50.pdf",
    "catalogue_page": 61,
    "catalogue_image_index": 60
  },
  {
    "id": "aarvi-standard-collection-61",
    "source_site": "shipmydeals",
    "url": "",
    "name": "Folding Wonder Vase",
    "category": "standard-collection",
    "category_label": "Standard Collection",
    "price": "",
    "price_numeric": 0,
    "description": "",
    "specifications": {},
    "images": [
      {
        "url": "",
        "local_path": "cropped/low-range-20-50/62.jpg",
        "filename": "62.jpg",
        "is_primary": true,
        "download_status": "success"
      }
    ],
    "scraped_at": "",
    "product_code": "E 54",
    "catalogue_pdf": "low-range-20-50.pdf",
    "catalogue_page": 62,
    "catalogue_image_index": 61
  },
  {
    "id": "aarvi-standard-collection-62",
    "source_site": "shipmydeals",
    "url": "",
    "name": "Extension Wire (cord",
    "category": "standard-collection",
    "category_label": "Standard Collection",
    "price": "",
    "price_numeric": 0,
    "description": "",
    "specifications": {},
    "images": [
      {
        "url": "",
        "local_path": "cropped/low-range-20-50/63.jpg",
        "filename": "63.jpg",
        "is_primary": true,
        "download_status": "success"
      }
    ],
    "scraped_at": "",
    "product_code": "E 10",
    "catalogue_pdf": "low-range-20-50.pdf",
    "catalogue_page": 63,
    "catalogue_image_index": 62
  },
  {
    "id": "aarvi-standard-collection-63",
    "source_site": "shipmydeals",
    "url": "",
    "name": "Hanging Visiting Card Holder",
    "category": "standard-collection",
    "category_label": "Standard Collection",
    "price": "",
    "price_numeric": 0,
    "description": "",
    "specifications": {},
    "images": [
      {
        "url": "",
        "local_path": "cropped/low-range-20-50/64.jpg",
        "filename": "64.jpg",
        "is_primary": true,
        "download_status": "success"
      }
    ],
    "scraped_at": "",
    "product_code": "B 12",
    "catalogue_pdf": "low-range-20-50.pdf",
    "catalogue_page": 64,
    "catalogue_image_index": 63
  },
  {
    "id": "aarvi-standard-collection-64",
    "source_site": "shipmydeals",
    "url": "",
    "name": "Shoe Shiner",
    "category": "standard-collection",
    "category_label": "Standard Collection",
    "price": "",
    "price_numeric": 0,
    "description": "",
    "specifications": {},
    "images": [
      {
        "url": "",
        "local_path": "cropped/low-range-20-50/65.jpg",
        "filename": "65.jpg",
        "is_primary": true,
        "download_status": "success"
      }
    ],
    "scraped_at": "",
    "product_code": "E 173",
    "catalogue_pdf": "low-range-20-50.pdf",
    "catalogue_page": 65,
    "catalogue_image_index": 64
  }
]